textfiles/__init__.py
textfiles/csv_file.py
textfiles/exceptions.py
textfiles/file_factory.py
textfiles/json_file.py
textfiles/text_file_parent.py
textfiles/txt_file.py
textfiles-0.0.7.dist-info/LICENSE
textfiles-0.0.7.dist-info/METADATA
textfiles-0.0.7.dist-info/WHEEL
textfiles-0.0.7.dist-info/top_level.txt
textfiles-0.0.7.dist-info/RECORD
