Metadata-Version: 2.1
Name: textfiles
Version: 0.0.7
Summary: Managing the text files txt, csv and json
Home-page: UNKNOWN
Author: Yael Ben Yair, Hemed Tov
Author-email: <yaelmadmon1011@gmail.com>, <hemedbz@gmail.com>
License: UNKNOWN
Keywords: python,text,file,csv,json,txt
Platform: UNKNOWN
Classifier: Development Status :: 3 - Alpha
Classifier: Intended Audience :: Developers
Classifier: Programming Language :: Python :: 3
Classifier: Operating System :: Unix
Classifier: Operating System :: MacOS :: MacOS X
Classifier: Operating System :: Microsoft :: Windows
License-File: LICENSE
